Metadata-Version: 2.0
Name: dc-campaign-finance-scraper
Version: 0.6.2
Summary: Provides data from http://www.ocf.dc.gov/serv/download.asp in a nicer way
Home-page: http://github.com/codefordc/dc-campaign-finance-scraper
Author: Saul Shanabrook
Author-email: s.shanabrook@gmail.com
License: UNKNOWN
Platform: UNKNOWN
Requires-Dist: requests
Requires-Dist: click
Requires-Dist: beautifulsoup4
Requires-Dist: retrying
Requires-Dist: tablib
